Metadata-Version: 1.0
Name: KirillConfig
Version: 6.6.6
Summary: Kirill config YEE
Home-page: UNKNOWN
Author: UNKNOWN
Author-email: fantiktop212@gmail.com
License: UNKNOWN
Platform: UNKNOWN
